{
  "_class": "symbolMaster",
  "allowsOverrides": true,
  "backgroundColor": {
    "_class": "color",
    "alpha": 1,
    "blue": 1,
    "green": 1,
    "red": 1
  },
  "booleanOperation": -1,
  "clippingMaskMode": 0,
  "do_objectID": "D5238805-A43D-4D46-9859-655CA7A5BEC6",
  "exportOptions": {
    "_class": "exportOptions",
    "exportFormats": [
      {
        "_class": "exportFormat",
        "absoluteSize": 0,
        "fileFormat": "svg",
        "name": "",
        "namingScheme": 0,
        "scale": 1,
        "visibleScaleType": 0
      },
      {
        "_class": "exportFormat",
        "absoluteSize": 0,
        "fileFormat": "pdf",
        "name": "",
        "namingScheme": 0,
        "scale": 1,
        "visibleScaleType": 0
      }
    ],
    "includedLayerIds": [
    ],
    "layerOptions": 0,
    "shouldTrim": false
  },
  "frame": {
    "_class": "rect",
    "constrainProportions": false,
    "height": 24,
    "width": 24,
    "x": -273,
    "y": -121
  },
  "groupLayout": {
    "_class": "MSImmutableFreeformGroupLayout"
  },
  "hasBackgroundColor": false,
  "hasClickThrough": true,
  "hasClippingMask": false,
  "horizontalRulerData": {
    "_class": "rulerData",
    "base": 0,
    "guides": [
    ]
  },
  "includeBackgroundColorInExport": true,
  "includeBackgroundColorInInstance": false,
  "isFixedToViewport": false,
  "isFlippedHorizontal": false,
  "isFlippedVertical": false,
  "isFlowHome": false,
  "isLocked": false,
  "isVisible": true,
  "layerListExpandedType": 2,
  "layers": [
    {
      "_class": "group",
      "booleanOperation": -1,
      "clippingMaskMode": 0,
      "do_objectID": "F6CBE7E5-59F2-4D5F-B60A-827049CCAA6B",
      "exportOptions": {
        "_class": "exportOptions",
        "exportFormats": [
        ],
        "includedLayerIds": [
        ],
        "layerOptions": 0,
        "shouldTrim": false
      },
      "frame": {
        "_class": "rect",
        "constrainProportions": true,
        "height": 14,
        "width": 20,
        "x": 2,
        "y": 5
      },
      "groupLayout": {
        "_class": "MSImmutableFreeformGroupLayout"
      },
      "hasClickThrough": false,
      "hasClippingMask": false,
      "isFixedToViewport": false,
      "isFlippedHorizontal": false,
      "isFlippedVertical": false,
      "isLocked": false,
      "isVisible": true,
      "layerListExpandedType": 0,
      "layers": [
        {
          "_class": "shapeGroup",
          "booleanOperation": -1,
          "clippingMaskMode": 0,
          "do_objectID": "1B558A9E-B81C-4545-946A-0978FE138BDF",
          "exportOptions": {
            "_class": "exportOptions",
            "exportFormats": [
            ],
            "includedLayerIds": [
            ],
            "layerOptions": 0,
            "shouldTrim": false
          },
          "frame": {
            "_class": "rect",
            "constrainProportions": false,
            "height": 14,
            "width": 19.63687150837989,
            "x": 0,
            "y": 0
          },
          "groupLayout": {
            "_class": "MSImmutableFreeformGroupLayout"
          },
          "hasClickThrough": false,
          "hasClippingMask": false,
          "isFixedToViewport": false,
          "isFlippedHorizontal": false,
          "isFlippedVertical": false,
          "isLocked": false,
          "isVisible": true,
          "layerListExpandedType": 1,
          "layers": [
            {
              "_class": "shapePath",
              "booleanOperation": -1,
              "clippingMaskMode": 0,
              "do_objectID": "9FFBA3CE-5C95-4D1E-B9EE-61C277297B8D",
              "edited": true,
              "exportOptions": {
                "_class": "exportOptions",
                "exportFormats": [
                ],
                "includedLayerIds": [
                ],
                "layerOptions": 0,
                "shouldTrim": false
              },
              "frame": {
                "_class": "rect",
                "constrainProportions": false,
                "height": 14,
                "width": 19.63687150837989,
                "x": 0,
                "y": 0
              },
              "hasClippingMask": false,
              "isClosed": true,
              "isFixedToViewport": false,
              "isFlippedHorizontal": false,
              "isFlippedVertical": false,
              "isLocked": false,
              "isVisible": true,
              "layerListExpandedType": 0,
              "name": "Path",
              "nameIsFixed": false,
              "pointRadiusBehaviour": 1,
              "points": [
                {
                  "_class": "curvePoint",
                  "cornerRadius": 0,
                  "curveFrom": "{0.98150782361308675, 0.94452347083926025}",
                  "curveMode": 4,
                  "curveTo": "{0.99170222854433365, 0.94452347083926025}",
                  "hasCurveFrom": false,
                  "hasCurveTo": true,
                  "point": "{0.98150782361308675, 0.94452347083926025}"
                },
                {
                  "_class": "curvePoint",
                  "cornerRadius": 0,
                  "curveFrom": "{0.036984352773826459, 0.94452347083926025}",
                  "curveMode": 1,
                  "curveTo": "{0.036984352773826459, 0.94452347083926025}",
                  "hasCurveFrom": false,
                  "hasCurveTo": false,
                  "point": "{0.036984352773826459, 0.94452347083926025}"
                },
                {
                  "_class": "curvePoint",
                  "cornerRadius": 0,
                  "curveFrom": "{0.036984352773826459, 0.10348506401137976}",
                  "curveMode": 1,
                  "curveTo": "{0.036984352773826459, 0.10348506401137976}",
                  "hasCurveFrom": false,
                  "hasCurveTo": false,
                  "point": "{0.036984352773826459, 0.10348506401137976}"
                },
                {
                  "_class": "curvePoint",
                  "cornerRadius": 0,
                  "curveFrom": "{0.4935988620199146, 0.49893314366998565}",
                  "curveMode": 4,
                  "curveTo": "{0.49075391180654337, 0.49644381223328582}",
                  "hasCurveFrom": true,
                  "hasCurveTo": false,
                  "point": "{0.49075391180654337, 0.49644381223328582}"
                },
                {
                  "_class": "curvePoint",
                  "cornerRadius": 0,
                  "curveFrom": "{0.50308202939781888, 0.49999999999999989}",
                  "curveMode": 2,
                  "curveTo": "{0.49691797060218112, 0.49999999999999989}",
                  "hasCurveFrom": true,
                  "hasCurveTo": true,
                  "point": "{0.5, 0.49999999999999989}"
                },
                {
                  "_class": "curvePoint",
                  "cornerRadius": 0,
                  "curveFrom": "{0.50924608819345663, 0.49644381223328582}",
                  "curveMode": 4,
                  "curveTo": "{0.50640113798008535, 0.49893314366998565}",
                  "hasCurveFrom": false,
                  "hasCurveTo": true,
                  "point": "{0.50924608819345663, 0.49644381223328582}"
                },
                {
                  "_class": "curvePoint",
                  "cornerRadius": 0,
                  "curveFrom": "{0.9630156472261735, 0.10384068278805116}",
                  "curveMode": 1,
                  "curveTo": "{0.9630156472261735, 0.10384068278805116}",
                  "hasCurveFrom": false,
                  "hasCurveTo": false,
                  "point": "{0.9630156472261735, 0.10384068278805116}"
                },
                {
                  "_class": "curvePoint",
                  "cornerRadius": 0,
                  "curveFrom": "{0.9630156472261735, 0.65433854907539113}",
                  "curveMode": 4,
                  "curveTo": "{0.9630156472261735, 0.63904694167852061}",
                  "hasCurveFrom": true,
                  "hasCurveTo": false,
                  "point": "{0.9630156472261735, 0.63904694167852061}"
                },
                {
                  "_class": "curvePoint",
                  "cornerRadius": 0,
                  "curveFrom": "{0.99170222854433376, 0.66678520625889048}",
                  "curveMode": 2,
                  "curveTo": "{0.97131341868183974, 0.66678520625889048}",
                  "hasCurveFrom": true,
                  "hasCurveTo": true,
                  "point": "{0.98150782361308675, 0.66678520625889048}"
                },
                {
                  "_class": "curvePoint",
                  "cornerRadius": 0,
                  "curveFrom": "{1, 0.63904694167852061}",
                  "curveMode": 4,
                  "curveTo": "{1, 0.65433854907539113}",
                  "hasCurveFrom": false,
                  "hasCurveTo": true,
                  "point": "{1, 0.63904694167852061}"
                },
                {
                  "_class": "curvePoint",
                  "cornerRadius": 0,
                  "curveFrom": "{1, 0.012446657183499287}",
                  "curveMode": 4,
                  "curveTo": "{1, 0.027738264580369831}",
                  "hasCurveFrom": true,
                  "hasCurveTo": false,
                  "point": "{1, 0.027738264580369831}"
                },
                {
                  "_class": "curvePoint",
                  "cornerRadius": 0,
                  "curveFrom": "{0.98150782361308675, 0}",
                  "curveMode": 4,
                  "curveTo": "{0.99170222854433376, 0}",
                  "hasCurveFrom": false,
                  "hasCurveTo": true,
                  "point": "{0.98150782361308675, 0}"
                },
                {
                  "_class": "curvePoint",
                  "cornerRadius": 0,
                  "curveFrom": "{0.0082977714556661929, 0}",
                  "curveMode": 4,
                  "curveTo": "{0.018492176386913223, 0}",
                  "hasCurveFrom": true,
                  "hasCurveTo": false,
                  "point": "{0.018492176386913223, 0}"
                },
                {
                  "_class": "curvePoint",
                  "cornerRadius": 0,
                  "curveFrom": "{0, 0.027738264580369831}",
                  "curveMode": 4,
                  "curveTo": "{0, 0.012446657183499287}",
                  "hasCurveFrom": false,
                  "hasCurveTo": true,
                  "point": "{0, 0.027738264580369831}"
                },
                {
                  "_class": "curvePoint",
                  "cornerRadius": 0,
                  "curveFrom": "{0, 0.98755334281650076}",
                  "curveMode": 4,
                  "curveTo": "{0, 0.9722617354196299}",
                  "hasCurveFrom": true,
                  "hasCurveTo": false,
                  "point": "{0, 0.9722617354196299}"
                },
                {
                  "_class": "curvePoint",
                  "cornerRadius": 0,
                  "curveFrom": "{0.018492176386913223, 1}",
                  "curveMode": 4,
                  "curveTo": "{0.0082977714556661929, 1}",
                  "hasCurveFrom": false,
                  "hasCurveTo": true,
                  "point": "{0.018492176386913223, 1}"
                },
                {
                  "_class": "curvePoint",
                  "cornerRadius": 0,
                  "curveFrom": "{0.99170222854433365, 1}",
                  "curveMode": 4,
                  "curveTo": "{0.98150782361308664, 1}",
                  "hasCurveFrom": true,
                  "hasCurveTo": false,
                  "point": "{0.98150782361308664, 1}"
                },
                {
                  "_class": "curvePoint",
                  "cornerRadius": 0,
                  "curveFrom": "{0.99999999999999989, 0.95697012802275949}",
                  "curveMode": 2,
                  "curveTo": "{0.99999999999999989, 0.98755334281650076}",
                  "hasCurveFrom": true,
                  "hasCurveTo": true,
                  "point": "{0.99999999999999989, 0.9722617354196299}"
                }
              ],
              "resizingConstraint": 63,
              "resizingType": 0,
              "rotation": 0,
              "shouldBreakMaskChain": false,
              "style": {
                "_class": "style",
                "blur": {
                  "_class": "blur",
                  "center": "{0.5, 0.5}",
                  "isEnabled": false,
                  "motionAngle": 0,
                  "radius": 10,
                  "saturation": 1,
                  "type": 0
                },
                "borderOptions": {
                  "_class": "borderOptions",
                  "dashPattern": [
                  ],
                  "isEnabled": true,
                  "lineCapStyle": 0,
                  "lineJoinStyle": 0
                },
                "borders": [
                ],
                "colorControls": {
                  "_class": "colorControls",
                  "brightness": 0,
                  "contrast": 1,
                  "hue": 0,
                  "isEnabled": false,
                  "saturation": 1
                },
                "contextSettings": {
                  "_class": "graphicsContextSettings",
                  "blendMode": 0,
                  "opacity": 1
                },
                "do_objectID": "33BE9128-863E-4FB8-98FA-DD2433EF49D9",
                "endMarkerType": 0,
                "fills": [
                ],
                "innerShadows": [
                ],
                "miterLimit": 10,
                "shadows": [
                ],
                "startMarkerType": 0,
                "windingRule": 1
              }
            },
            {
              "_class": "shapePath",
              "booleanOperation": -1,
              "clippingMaskMode": 0,
              "do_objectID": "DD1268C7-EC38-4F03-9278-14E915535DAC",
              "edited": true,
              "exportOptions": {
                "_class": "exportOptions",
                "exportFormats": [
                ],
                "includedLayerIds": [
                ],
                "layerOptions": 0,
                "shouldTrim": false
              },
              "frame": {
                "_class": "rect",
                "constrainProportions": false,
                "height": 5.386913229018491,
                "width": 17.45810055865921,
                "x": 1.089385474860335,
                "y": 0.7766714082503552
              },
              "hasClippingMask": false,
              "isClosed": true,
              "isFixedToViewport": false,
              "isFlippedHorizontal": false,
              "isFlippedVertical": false,
              "isLocked": false,
              "isVisible": true,
              "layerListExpandedType": 0,
              "name": "Path",
              "nameIsFixed": false,
              "pointRadiusBehaviour": 1,
              "points": [
                {
                  "_class": "curvePoint",
                  "cornerRadius": 0,
                  "curveFrom": "{0.5, 1}",
                  "curveMode": 1,
                  "curveTo": "{0.5, 1}",
                  "hasCurveFrom": false,
                  "hasCurveTo": false,
                  "point": "{0.5, 1}"
                },
                {
                  "_class": "curvePoint",
                  "cornerRadius": 0,
                  "curveFrom": "{0, 0}",
                  "curveMode": 1,
                  "curveTo": "{0, 0}",
                  "hasCurveFrom": false,
                  "hasCurveTo": false,
                  "point": "{0, 0}"
                },
                {
                  "_class": "curvePoint",
                  "cornerRadius": 0,
                  "curveFrom": "{1, 0}",
                  "curveMode": 1,
                  "curveTo": "{1, 0}",
                  "hasCurveFrom": false,
                  "hasCurveTo": false,
                  "point": "{1, 0}"
                }
              ],
              "resizingConstraint": 63,
              "resizingType": 0,
              "rotation": 0,
              "shouldBreakMaskChain": false,
              "style": {
                "_class": "style",
                "blur": {
                  "_class": "blur",
                  "center": "{0.5, 0.5}",
                  "isEnabled": false,
                  "motionAngle": 0,
                  "radius": 10,
                  "saturation": 1,
                  "type": 0
                },
                "borderOptions": {
                  "_class": "borderOptions",
                  "dashPattern": [
                  ],
                  "isEnabled": true,
                  "lineCapStyle": 0,
                  "lineJoinStyle": 0
                },
                "borders": [
                ],
                "colorControls": {
                  "_class": "colorControls",
                  "brightness": 0,
                  "contrast": 1,
                  "hue": 0,
                  "isEnabled": false,
                  "saturation": 1
                },
                "contextSettings": {
                  "_class": "graphicsContextSettings",
                  "blendMode": 0,
                  "opacity": 1
                },
                "do_objectID": "EBECB830-2197-46E4-A7B2-4F2EC3142D2C",
                "endMarkerType": 0,
                "fills": [
                ],
                "innerShadows": [
                ],
                "miterLimit": 10,
                "shadows": [
                ],
                "startMarkerType": 0,
                "windingRule": 1
              }
            }
          ],
          "name": "Shape",
          "nameIsFixed": false,
          "resizingConstraint": 63,
          "resizingType": 0,
          "rotation": 0,
          "shouldBreakMaskChain": false,
          "style": {
            "_class": "style",
            "blur": {
              "_class": "blur",
              "center": "{0.5, 0.5}",
              "isEnabled": false,
              "motionAngle": 0,
              "radius": 10,
              "saturation": 1,
              "type": 0
            },
            "borderOptions": {
              "_class": "borderOptions",
              "dashPattern": [
              ],
              "isEnabled": true,
              "lineCapStyle": 0,
              "lineJoinStyle": 0
            },
            "borders": [
            ],
            "colorControls": {
              "_class": "colorControls",
              "brightness": 0,
              "contrast": 1,
              "hue": 0,
              "isEnabled": false,
              "saturation": 1
            },
            "contextSettings": {
              "_class": "graphicsContextSettings",
              "blendMode": 0,
              "opacity": 1
            },
            "do_objectID": "44413A93-3FEF-4304-8740-CCC5BCBE041B",
            "endMarkerType": 0,
            "fills": [
              {
                "_class": "fill",
                "color": {
                  "_class": "color",
                  "alpha": 1,
                  "blue": 0.6470588235294118,
                  "green": 0.09803921568627451,
                  "red": 0
                },
                "contextSettings": {
                  "_class": "graphicsContextSettings",
                  "blendMode": 0,
                  "opacity": 1
                },
                "fillType": 0,
                "gradient": {
                  "_class": "gradient",
                  "elipseLength": 0,
                  "from": "{0.5, 0}",
                  "gradientType": 0,
                  "stops": [
                    {
                      "_class": "gradientStop",
                      "color": {
                        "_class": "color",
                        "alpha": 1,
                        "blue": 1,
                        "green": 1,
                        "red": 1
                      },
                      "position": 0
                    },
                    {
                      "_class": "gradientStop",
                      "color": {
                        "_class": "color",
                        "alpha": 1,
                        "blue": 0,
                        "green": 0,
                        "red": 0
                      },
                      "position": 1
                    }
                  ],
                  "to": "{0.5, 1}"
                },
                "isEnabled": true,
                "noiseIndex": 0,
                "noiseIntensity": 0,
                "patternFillType": 1,
                "patternTileScale": 1
              }
            ],
            "innerShadows": [
            ],
            "miterLimit": 10,
            "shadows": [
            ],
            "startMarkerType": 0,
            "windingRule": 0
          },
          "windingRule": 0
        },
        {
          "_class": "oval",
          "booleanOperation": -1,
          "clippingMaskMode": 0,
          "do_objectID": "A9E427CB-0963-4B3E-9E6A-607C9B630A59",
          "edited": false,
          "exportOptions": {
            "_class": "exportOptions",
            "exportFormats": [
            ],
            "includedLayerIds": [
            ],
            "layerOptions": 0,
            "shouldTrim": false
          },
          "frame": {
            "_class": "rect",
            "constrainProportions": false,
            "height": 1.553342816500713,
            "width": 1.452513966480446,
            "x": 18.54748603351955,
            "y": 10.49999999999999
          },
          "hasClippingMask": false,
          "isClosed": true,
          "isFixedToViewport": false,
          "isFlippedHorizontal": false,
          "isFlippedVertical": false,
          "isLocked": false,
          "isVisible": true,
          "layerListExpandedType": 0,
          "name": "Oval",
          "nameIsFixed": false,
          "pointRadiusBehaviour": 1,
          "points": [
            {
              "_class": "curvePoint",
              "cornerRadius": 0,
              "curveFrom": "{0.77614237490000004, 1}",
              "curveMode": 2,
              "curveTo": "{0.22385762510000001, 1}",
              "hasCurveFrom": true,
              "hasCurveTo": true,
              "point": "{0.5, 1}"
            },
            {
              "_class": "curvePoint",
              "cornerRadius": 0,
              "curveFrom": "{1, 0.22385762510000001}",
              "curveMode": 2,
              "curveTo": "{1, 0.77614237490000004}",
              "hasCurveFrom": true,
              "hasCurveTo": true,
              "point": "{1, 0.5}"
            },
            {
              "_class": "curvePoint",
              "cornerRadius": 0,
              "curveFrom": "{0.22385762510000001, 0}",
              "curveMode": 2,
              "curveTo": "{0.77614237490000004, 0}",
              "hasCurveFrom": true,
              "hasCurveTo": true,
              "point": "{0.5, 0}"
            },
            {
              "_class": "curvePoint",
              "cornerRadius": 0,
              "curveFrom": "{0, 0.77614237490000004}",
              "curveMode": 2,
              "curveTo": "{0, 0.22385762510000001}",
              "hasCurveFrom": true,
              "hasCurveTo": true,
              "point": "{0, 0.5}"
            }
          ],
          "resizingConstraint": 63,
          "resizingType": 0,
          "rotation": 0,
          "shouldBreakMaskChain": false,
          "style": {
            "_class": "style",
            "blur": {
              "_class": "blur",
              "center": "{0.5, 0.5}",
              "isEnabled": false,
              "motionAngle": 0,
              "radius": 10,
              "saturation": 1,
              "type": 0
            },
            "borderOptions": {
              "_class": "borderOptions",
              "dashPattern": [
              ],
              "isEnabled": true,
              "lineCapStyle": 0,
              "lineJoinStyle": 0
            },
            "borders": [
            ],
            "colorControls": {
              "_class": "colorControls",
              "brightness": 0,
              "contrast": 1,
              "hue": 0,
              "isEnabled": false,
              "saturation": 1
            },
            "contextSettings": {
              "_class": "graphicsContextSettings",
              "blendMode": 0,
              "opacity": 1
            },
            "do_objectID": "B47FEB34-23EC-4112-9BC7-5B4A4844EE5A",
            "endMarkerType": 0,
            "fills": [
              {
                "_class": "fill",
                "color": {
                  "_class": "color",
                  "alpha": 1,
                  "blue": 0.6470588235294118,
                  "green": 0.09803921568627451,
                  "red": 0
                },
                "contextSettings": {
                  "_class": "graphicsContextSettings",
                  "blendMode": 0,
                  "opacity": 1
                },
                "fillType": 0,
                "gradient": {
                  "_class": "gradient",
                  "elipseLength": 0,
                  "from": "{0.5, 0}",
                  "gradientType": 0,
                  "stops": [
                    {
                      "_class": "gradientStop",
                      "color": {
                        "_class": "color",
                        "alpha": 1,
                        "blue": 1,
                        "green": 1,
                        "red": 1
                      },
                      "position": 0
                    },
                    {
                      "_class": "gradientStop",
                      "color": {
                        "_class": "color",
                        "alpha": 1,
                        "blue": 0,
                        "green": 0,
                        "red": 0
                      },
                      "position": 1
                    }
                  ],
                  "to": "{0.5, 1}"
                },
                "isEnabled": true,
                "noiseIndex": 0,
                "noiseIntensity": 0,
                "patternFillType": 1,
                "patternTileScale": 1
              }
            ],
            "innerShadows": [
            ],
            "miterLimit": 10,
            "shadows": [
            ],
            "startMarkerType": 0,
            "windingRule": 0
          }
        }
      ],
      "name": "Envelope _1Primary",
      "nameIsFixed": false,
      "resizingConstraint": 63,
      "resizingType": 0,
      "rotation": 0,
      "shouldBreakMaskChain": false,
      "style": {
        "_class": "style",
        "blur": {
          "_class": "blur",
          "center": "{0.5, 0.5}",
          "isEnabled": false,
          "motionAngle": 0,
          "radius": 10,
          "saturation": 1,
          "type": 0
        },
        "borderOptions": {
          "_class": "borderOptions",
          "dashPattern": [
          ],
          "isEnabled": true,
          "lineCapStyle": 0,
          "lineJoinStyle": 0
        },
        "borders": [
        ],
        "colorControls": {
          "_class": "colorControls",
          "brightness": 0,
          "contrast": 1,
          "hue": 0,
          "isEnabled": false,
          "saturation": 1
        },
        "contextSettings": {
          "_class": "graphicsContextSettings",
          "blendMode": 0,
          "opacity": 1
        },
        "do_objectID": "2192CE0E-5A44-4B40-BF2D-D58FE5A495D9",
        "endMarkerType": 0,
        "fills": [
        ],
        "innerShadows": [
        ],
        "miterLimit": 10,
        "shadows": [
        ],
        "startMarkerType": 0,
        "windingRule": 1
      }
    }
  ],
  "name": "o2/1.Light/email-light",
  "nameIsFixed": false,
  "overrideProperties": [
    {
      "_class": "MSImmutableOverrideProperty",
      "canOverride": true,
      "overrideName": "09CB3BCC-7C8E-4ED8-A83B-F79AC621766A_layerStyle"
    }
  ],
  "presetDictionary": {
  },
  "resizesContent": false,
  "resizingConstraint": 63,
  "resizingType": 0,
  "rotation": 0,
  "shouldBreakMaskChain": true,
  "style": {
    "_class": "style",
    "blur": {
      "_class": "blur",
      "center": "{0.5, 0.5}",
      "isEnabled": false,
      "motionAngle": 0,
      "radius": 0.3361344537815126,
      "saturation": 1,
      "type": 0
    },
    "borderOptions": {
      "_class": "borderOptions",
      "dashPattern": [
      ],
      "isEnabled": true,
      "lineCapStyle": 0,
      "lineJoinStyle": 0
    },
    "borders": [
    ],
    "colorControls": {
      "_class": "colorControls",
      "brightness": 0,
      "contrast": 1,
      "hue": 0,
      "isEnabled": false,
      "saturation": 1
    },
    "contextSettings": {
      "_class": "graphicsContextSettings",
      "blendMode": 0,
      "opacity": 1
    },
    "do_objectID": "A52C50EC-5E42-4FD8-AAA7-0EBC5DC9AE2E",
    "endMarkerType": 0,
    "fills": [
    ],
    "innerShadows": [
    ],
    "miterLimit": 10,
    "shadows": [
    ],
    "startMarkerType": 0,
    "windingRule": 1
  },
  "symbolID": "4FD0267D-ED1E-40ED-8AED-6AB714F296F4",
  "verticalRulerData": {
    "_class": "rulerData",
    "base": 0,
    "guides": [
    ]
  }
}