{
  "_class": "shapePath",
  "booleanOperation": -1,
  "clippingMaskMode": 0,
  "do_objectID": "F2B5111E-1F97-408B-9C80-21FD8BEE4578",
  "edited": true,
  "exportOptions": {
    "_class": "exportOptions",
    "exportFormats": [
    ],
    "includedLayerIds": [
    ],
    "layerOptions": 0,
    "shouldTrim": false
  },
  "frame": {
    "_class": "rect",
    "constrainProportions": false,
    "height": 5.045378151260504,
    "width": 5.089267358799274,
    "x": 2.557897237697957,
    "y": 10.30387729473185
  },
  "hasClippingMask": false,
  "isClosed": true,
  "isFixedToViewport": false,
  "isFlippedHorizontal": false,
  "isFlippedVertical": false,
  "isLocked": false,
  "isVisible": true,
  "layerListExpandedType": 1,
  "name": "Path",
  "nameIsFixed": false,
  "pointRadiusBehaviour": 1,
  "points": [
    {
      "_class": "curvePoint",
      "cornerRadius": 0,
      "curveFrom": "{1.0204587782487131, 0.33177881412391741}",
      "curveMode": 4,
      "curveTo": "{0.85732093495878636, 0.16389073950699545}",
      "hasCurveFrom": true,
      "hasCurveTo": false,
      "point": "{0.85732093495878636, 0.16389073950699545}"
    },
    {
      "_class": "curvePoint",
      "cornerRadius": 0,
      "curveFrom": "{0.71267645042237349, 0.97268487674883397}",
      "curveMode": 3,
      "curveTo": "{1.0785807629026143, 0.60626249167221846}",
      "hasCurveFrom": true,
      "hasCurveTo": true,
      "point": "{0.8421299616969713, 0.84277148567621574}"
    },
    {
      "_class": "curvePoint",
      "cornerRadius": 0,
      "curveFrom": "{0.32761830209027876, 1}",
      "curveMode": 3,
      "curveTo": "{0.58256246204943574, 1}",
      "hasCurveFrom": true,
      "hasCurveTo": true,
      "point": "{0.49603996216692392, 1}"
    },
    {
      "_class": "curvePoint",
      "cornerRadius": 0,
      "curveFrom": "{0.15589425652193484, 0.84876748834110605}",
      "curveMode": 4,
      "curveTo": "{0.20807194729077771, 0.90006662225183209}",
      "hasCurveFrom": true,
      "hasCurveTo": true,
      "point": "{0.16381998170201217, 0.85676215856095939}"
    },
    {
      "_class": "curvePoint",
      "cornerRadius": 0,
      "curveFrom": "{-0.019792651636448107, 0.66422385076615609}",
      "curveMode": 4,
      "curveTo": "{0.14796853134185731, 0.84143904063957353}",
      "hasCurveFrom": true,
      "hasCurveTo": true,
      "point": "{0.14070328326011972, 0.83344437041972019}"
    },
    {
      "_class": "curvePoint",
      "cornerRadius": 0,
      "curveFrom": "{0.28402681359985316, 0.026648900732844767}",
      "curveMode": 3,
      "curveTo": "{-0.077914636290349074, 0.38907395069953382}",
      "hasCurveFrom": true,
      "hasCurveTo": true,
      "point": "{0.15589425652193484, 0.15522984676882084}"
    },
    {
      "_class": "curvePoint",
      "cornerRadius": 0,
      "curveFrom": "{0.66842448483360795, 0}",
      "curveMode": 3,
      "curveTo": "{0.41348032487445097, 0}",
      "hasCurveFrom": true,
      "hasCurveTo": true,
      "point": "{0.50000282475696278, 0}"
    },
    {
      "_class": "curvePoint",
      "cornerRadius": 0,
      "curveFrom": "{0.84146948459863136, 0.14790139906728839}",
      "curveMode": 4,
      "curveTo": "{0.78929179382978842, 0.098600932711525716}",
      "hasCurveFrom": true,
      "hasCurveTo": true,
      "point": "{0.83354375941855396, 0.1412391738840772}"
    },
    {
      "_class": "curvePoint",
      "cornerRadius": 0,
      "curveFrom": "{0.85732093495878636, 0.16389073950699509}",
      "curveMode": 4,
      "curveTo": "{0.85005568687704858, 0.15656229180546299}",
      "hasCurveFrom": false,
      "hasCurveTo": true,
      "point": "{0.85732093495878636, 0.16389073950699509}"
    }
  ],
  "resizingConstraint": 63,
  "resizingType": 0,
  "rotation": 0,
  "shouldBreakMaskChain": false,
  "style": {
    "_class": "style",
    "blur": {
      "_class": "blur",
      "center": "{0.5, 0.5}",
      "isEnabled": false,
      "motionAngle": 0,
      "radius": 10,
      "saturation": 1,
      "type": 0
    },
    "borderOptions": {
      "_class": "borderOptions",
      "dashPattern": [
      ],
      "isEnabled": true,
      "lineCapStyle": 0,
      "lineJoinStyle": 0
    },
    "borders": [
    ],
    "colorControls": {
      "_class": "colorControls",
      "brightness": 0,
      "contrast": 1,
      "hue": 0,
      "isEnabled": true,
      "saturation": 1
    },
    "contextSettings": {
      "_class": "graphicsContextSettings",
      "blendMode": 0,
      "opacity": 1
    },
    "do_objectID": "A1BD83B1-FA2D-4047-8687-1802509B54B7",
    "endMarkerType": 0,
    "fills": [
      {
        "_class": "fill",
        "color": {
          "_class": "color",
          "alpha": 1,
          "blue": 0.08235294117647059,
          "green": 0.7137254901960784,
          "red": 0.3607843137254902
        },
        "contextSettings": {
          "_class": "graphicsContextSettings",
          "blendMode": 0,
          "opacity": 1
        },
        "fillType": 0,
        "gradient": {
          "_class": "gradient",
          "elipseLength": 0,
          "from": "{0.5, 0}",
          "gradientType": 0,
          "stops": [
            {
              "_class": "gradientStop",
              "color": {
                "_class": "color",
                "alpha": 1,
                "blue": 1,
                "green": 1,
                "red": 1
              },
              "position": 0
            },
            {
              "_class": "gradientStop",
              "color": {
                "_class": "color",
                "alpha": 1,
                "blue": 0,
                "green": 0,
                "red": 0
              },
              "position": 1
            }
          ],
          "to": "{0.5, 1}"
        },
        "isEnabled": true,
        "noiseIndex": 0,
        "noiseIntensity": 0,
        "patternFillType": 1,
        "patternTileScale": 1
      }
    ],
    "innerShadows": [
    ],
    "miterLimit": 10,
    "shadows": [
    ],
    "startMarkerType": 0,
    "windingRule": 0
  }
}